layer_proto/__init__.py
layer_proto/amino/__init__.py
layer_proto/cosmos/__init__.py
layer_proto/cosmos/app/__init__.py
layer_proto/cosmos/app/runtime/__init__.py
layer_proto/cosmos/app/runtime/v1alpha1/__init__.py
layer_proto/cosmos/app/v1alpha1/__init__.py
layer_proto/cosmos/auth/__init__.py
layer_proto/cosmos/auth/module/__init__.py
layer_proto/cosmos/auth/module/v1/__init__.py
layer_proto/cosmos/auth/v1beta1/__init__.py
layer_proto/cosmos/authz/__init__.py
layer_proto/cosmos/authz/module/__init__.py
layer_proto/cosmos/authz/module/v1/__init__.py
layer_proto/cosmos/authz/v1beta1/__init__.py
layer_proto/cosmos/autocli/__init__.py
layer_proto/cosmos/autocli/v1/__init__.py
layer_proto/cosmos/bank/__init__.py
layer_proto/cosmos/bank/module/__init__.py
layer_proto/cosmos/bank/module/v1/__init__.py
layer_proto/cosmos/bank/v1beta1/__init__.py
layer_proto/cosmos/base/__init__.py
layer_proto/cosmos/base/abci/__init__.py
layer_proto/cosmos/base/abci/v1beta1/__init__.py
layer_proto/cosmos/base/node/__init__.py
layer_proto/cosmos/base/node/v1beta1/__init__.py
layer_proto/cosmos/base/query/__init__.py
layer_proto/cosmos/base/query/v1beta1/__init__.py
layer_proto/cosmos/base/reflection/__init__.py
layer_proto/cosmos/base/reflection/v1beta1/__init__.py
layer_proto/cosmos/base/reflection/v2alpha1/__init__.py
layer_proto/cosmos/base/tendermint/__init__.py
layer_proto/cosmos/base/tendermint/v1beta1/__init__.py
layer_proto/cosmos/base/v1beta1/__init__.py
layer_proto/cosmos/circuit/__init__.py
layer_proto/cosmos/circuit/module/__init__.py
layer_proto/cosmos/circuit/module/v1/__init__.py
layer_proto/cosmos/circuit/v1/__init__.py
layer_proto/cosmos/consensus/__init__.py
layer_proto/cosmos/consensus/module/__init__.py
layer_proto/cosmos/consensus/module/v1/__init__.py
layer_proto/cosmos/consensus/v1/__init__.py
layer_proto/cosmos/crisis/__init__.py
layer_proto/cosmos/crisis/module/__init__.py
layer_proto/cosmos/crisis/module/v1/__init__.py
layer_proto/cosmos/crisis/v1beta1/__init__.py
layer_proto-0.1.0.dist-info/METADATA
layer_proto-0.1.0.dist-info/WHEEL
layer_proto-0.1.0.dist-info/top_level.txt
layer_proto-0.1.0.dist-info/RECORD
